ProbStatipy/__init__.py
ProbStatipy/central.py
ProbStatipy/spread.py
ProbStatipy-0.0.5.dist-info/LICENCE.txt
ProbStatipy-0.0.5.dist-info/METADATA
ProbStatipy-0.0.5.dist-info/WHEEL
ProbStatipy-0.0.5.dist-info/top_level.txt
ProbStatipy-0.0.5.dist-info/RECORD
