Metadata-Version: 2.1
Name: ProbStatipy
Version: 0.0.5
Summary: A Python package to compute probabilities and statistics
Author-email: GREGORY OCHIENG OPONDI <ds4gregory@gmail.com>
Project-URL: Homepage, https://github.com/0gregory0/ProbStatipy
Project-URL: Issues, https://github.com/0gregory0/ProbStatipy/issues
Classifier: Programming Language :: Python :: 3
Classifier: License :: OSI Approved :: Apache Software License
Classifier: Operating System :: OS Independent
Requires-Python: >=3.8
License-File: LICENCE.txt
